Flask_Session_Imp-0.0.1.dist-info/DESCRIPTION.rst
Flask_Session_Imp-0.0.1.dist-info/METADATA
Flask_Session_Imp-0.0.1.dist-info/RECORD
Flask_Session_Imp-0.0.1.dist-info/WHEEL
Flask_Session_Imp-0.0.1.dist-info/metadata.json
Flask_Session_Imp-0.0.1.dist-info/top_level.txt
flask_session_imp/__init__.py
flask_session_imp/sessions.py
