Metadata-Version: 2.0
Name: Flask-Session-Imp
Version: 0.0.1
Summary: Adds server-side session support to your Flask application
Home-page: https://github.com/mikezone/flask-session
Author: mike_chang
Author-email: 82643885@qq.com
License: BSD
Platform: any
Classifier: Environment :: Web Environment
Classifier: Intended Audience :: Developers
Classifier: License :: OSI Approved :: BSD License
Classifier: Operating System :: OS Independent
Classifier: Programming Language :: Python :: 2
Classifier: Topic :: Internet :: WWW/HTTP :: Dynamic Content
Classifier: Topic :: Software Development :: Libraries :: Python Modules
Requires-Dist: Flask (>=0.8)
